rest_action_permissions/__init__.py
rest_action_permissions/__version__.py
rest_action_permissions/permissions.py
django_rest_action_permissions-2.0.0.dist-info/AUTHORS.rst
django_rest_action_permissions-2.0.0.dist-info/LICENSE
django_rest_action_permissions-2.0.0.dist-info/METADATA
django_rest_action_permissions-2.0.0.dist-info/WHEEL
django_rest_action_permissions-2.0.0.dist-info/top_level.txt
django_rest_action_permissions-2.0.0.dist-info/RECORD
