Metadata-Version: 2.1
Name: django-rest-action-permissions
Version: 2.0.0
Summary: Action based permissions for Django REST Framework.
Home-page: https://github.com/apirobot/django-rest-action-permissions
Author: Denis Orehovsky
Author-email: denis.orehovsky@gmail.com
License: MIT License
Platform: UNKNOWN
Classifier: License :: OSI Approved :: MIT License
Classifier: Intended Audience :: Developers
Classifier: Framework :: Django
Classifier: Framework :: Django :: 1.11
Classifier: Framework :: Django :: 2.0
Classifier: Programming Language :: Python
Classifier: Programming Language :: Python :: 2.7
Classifier: Programming Language :: Python :: 3.5
Classifier: Programming Language :: Python :: 3.6
Classifier: Programming Language :: Python :: Implementation :: CPython
Classifier: Programming Language :: Python :: Implementation :: PyPy
Requires-Dist: django
Requires-Dist: djangorestframework
Requires-Dist: six
